RV32I_Pipeline/REGISTERFILE.v
module REGISTERFILE #(
	parameter d_width = 32,
	parameter a_width = 5
)
(
	input clk, rst_n,
	input wen,
	input [a_width -1 : 0] raddr1, raddr2,
	input [a_width -1 : 0] waddr,
	input [d_width -1 : 0] wdata,
	
	output [d_width -1 : 0] rdata1,
	output [d_width -1 : 0] rdata2
);

reg [d_width -1 : 0] mem [0 : ((1 << a_width) -1 )];
integer i;
always @(posedge clk, negedge rst_n) begin
	if(!rst_n) begin
		for(i = 0; i < (1 << a_width); i = i + 1) begin
			mem[i] <= 32'd0;
		end
	end
	else begin
		if(wen) begin
			mem[waddr] <= wdata;
		end
	end
end

assign rdata1 = mem[raddr1];
assign rdata2 = mem[raddr2];

endmodule

REGISTERFILE_tb.v
`timescale 1ps/1ps
`include "REGISTERFILE.v"

module REGISTERFILE_tb;

parameter d_width = 32;
parameter a_width = 5;

reg clk, rst_n;
reg wen;
reg [a_width -1 : 0] raddr1, raddr2;
reg [a_width -1 : 0] waddr;
reg [d_width -1 : 0] wdata;
	
wire [d_width -1 : 0] rdata1;
wire [d_width -1 : 0] rdata2;

REGISTERFILE #(
    .d_width(d_width),
    .a_width(a_width)
)
dut(
    .clk(clk),
    .rst_n(rst_n),
    .wen(wen),
    .raddr1(raddr1),
    .raddr2(raddr2),
    .waddr(waddr),
    .wdata(wdata),
    .rdata1(rdata1),
    .rdata2(rdata2)
);

always #5 clk = ~clk;

initial begin

    $dumpfile("REGISTERFILE_tb.vcd");
    $dumpvars(0, REGISTERFILE_tb);

    clk = 0;
    rst_n = 1;
    raddr1 = 0;
    raddr2 = 0;
    waddr = 0;
    wen = 0;
    wdata = 0;

    #10 rst_n = 0;
    #10 rst_n = 1;

    #10

    wen = 1;
    waddr = 1;
    wdata = 10;

    #10
    waddr = 2;
    wdata = 20;

    #10
    waddr = 20;
    wdata = 40;

    #10
    wen = 0;

    #10     
    raddr1 = 1;
    raddr2 = 2;
    
    #10
    raddr1 = 20;
    #10;

    $finish;
end

endmodule

RV32I_Pipeline/REGISTERFILE_tb.vcd
$date
	Sat Apr 05 11:50:26 2025
$end
$version
	Icarus Verilog
$end
$timescale
	1ps
$end
$scope module REGISTERFILE_tb $end
$var wire 32 ! rdata2 [31:0] $end
$var wire 32 " rdata1 [31:0] $end
$var reg 1 # clk $end
$var reg 5 $ raddr1 [4:0] $end
$var reg 5 % raddr2 [4:0] $end
$var reg 1 & rst_n $end
$var reg 5 ' waddr [4:0] $end
$var reg 32 ( wdata [31:0] $end
$var reg 1 ) wen $end
$scope module dut $end
$var wire 1 # clk $end
$var wire 5 * raddr1 [4:0] $end
$var wire 5 + raddr2 [4:0] $end
$var wire 32 , rdata1 [31:0] $end
$var wire 32 - rdata2 [31:0] $end
$var wire 1 & rst_n $end
$var wire 5 . waddr [4:0] $end
$var wire 32 / wdata [31:0] $end
$var wire 1 ) wen $end
$var integer 32 0 i [31:0] $end
$upscope $end
$upscope $end
$enddefinitions $end
#0
$dumpvars
bx 0
b0 /
b0 .
bx -
bx ,
b0 +
b0 *
0)
b0 (
b0 '
1&
b0 %
b0 $
0#
bx "
bx !
$end
#5
1#
#10
b0 "
b0 ,
b0 !
b0 -
b100000 0
0#
0&
#15
b100000 0
1#
#20
0#
1&
#25
1#
#30
0#
b1010 (
b1010 /
b1 '
b1 .
1)
#35
1#
#40
0#
b10100 (
b10100 /
b10 '
b10 .
#45
1#
#50
0#
b101000 (
b101000 /
b10100 '
b10100 .
#55
1#
#60
0#
0)
#65
1#
#70
0#
b10100 !
b10100 -
b10 %
b10 +
b1010 "
b1010 ,
b1 $
b1 *
#75
1#
#80
0#
b101000 "
b101000 ,
b10100 $
b10100 *
